{
  "users": [
    {
      "id": "1",
      "name": "Николай Анисимов",
      "age": "21",
      "description": "Сильный и красивый. Умный и добрый. Одним словом - идеал!",
      "friends": "1",
      "friendList": [
        {
          "name": "Анжелика Милославская",
          "id": "3"
        }
      ]
    },
    {
      "id": "2",
      "name": "Андрей Белоусов",
      "age": "29",
      "description": "Люблю аниме, музыку и смотреть на звезды. Ищу друзей по интересам.",
      "friends": "4",
      "friendList": [
        {
          "name": "Анжелика Милославская",
          "id": "3"
        },
        {
          "name": "Виктор Эчпочмаков",
          "id": "4"
        },
        {
          "name": "Ульяна Медведева",
          "id": "5"
        },
        {
          "name": "Павел Комаров",
          "id": "6"
        }
      ]
    },
    {
      "id": "3",
      "name": "Анжелика Милославская",
      "age": "31",
      "description": "Я прекрасно понимаю, что я не самая лучшая женщина в мире, но это смотря в чьем мире.",
      "friends": "5",
      "friendList": [
        {
          "name": "Николай Анисимов",
          "id": "1"
        },
        {
          "name": "Андрей Белоусов",
          "id": "2"
        },
        {
          "name": "Павел Комаров",
          "id": "6"
        },
        {
          "name": "Виктория Птушкина",
          "id": "7"
        },
        {
          "name": "Виктор Эчпочмаков",
          "id": "4"
        }
      ]
    },
    {
      "id": "4",
      "name": "Виктор Эчпочмаков",
      "age": "19",
      "description": "Я - человек, для которого уединение жизненно необходимо.",
      "friends": "2",
      "friendList": [
        {
          "name": "Андрей Белоусов",
          "id": "2"
        },
        {
          "name": "Анжелика Милославская",
          "id": "3"
        }
      ]
    },
    {
      "id": "5",
      "name": "Ульяна Медведева",
      "age": "26",
      "description": "Я никому не буду доказывать, что я хорошая. Пусть мне попробуют доказать, что я плохая.",
      "friends": "3",
      "friendList": [
        {
          "name": "Андрей Белоусов",
          "id": "2"
        },
        {
          "name": "Павел Комаров",
          "id": "6"
        },
        {
          "name": "Виктория Птушкина",
          "id": "7"
        }
      ]
    },
    {
      "id": "6",
      "name": "Павел Комаров",
      "age": "29",
      "description": "Я вообще в этой жизни люблю только пирожки с вишней. Взаимностью не отвечают, но и как люди себя не ведут.",
      "friends": "4",
      "friendList": [
        {
          "name": "Андрей Белоусов",
          "id": "2"
        },
        {
          "name": "Ульяна Медведева",
          "id": "5"
        },
        {
          "name": "Виктория Птушкина",
          "id": "7"
        },
        {
          "name": "Анжелика Милославская",
          "id": "3"
        }
      ]
    },
    {
      "id": "7",
      "name": "Виктория Птушкина",
      "age": "34",
      "description": "Не слушаю тех, кто говорит, что я трачу жизнь впустую, ведь я хотя бы живу, а кто-то говорит.",
      "friends": "3",
      "friendList": [
        {
          "name": "Ульяна Медведева",
          "id": "5"
        },
        {
          "name": "Павел Комаров",
          "id": "6"
        },
        {
          "name": "Анжелика Милославская",
          "id": "3"
        }
      ]
    }
  ]
}